{
	"info": {
		"_postman_id": "a63c4626-e986-47a9-8a91-671d4804fac1",
		"name": "Code Elevate",
		"schema": "https://schema.getpostman.com/json/collection/v2.1.0/collection.json",
		"_exporter_id": "45336446"
	},
	"item": [
		{
			"name": "Get All Books",
			"request": {
				"auth": {
					"type": "bearer",
					"bearer": [
						{
							"key": "token",
							"value": "{{access_token}}",
							"type": "string"
						}
					]
				},
				"method": "GET",
				"header": [],
				"url": {
					"raw": "http://localhost:8080/books?page=0&size=20",
					"protocol": "http",
					"host": [
						"localhost"
					],
					"port": "8080",
					"path": [
						"books"
					],
					"query": [
						{
							"key": "page",
							"value": "0"
						},
						{
							"key": "size",
							"value": "20"
						}
					]
				}
			},
			"response": []
		},
		{
			"name": "Get Book By Id",
			"request": {
				"auth": {
					"type": "bearer",
					"bearer": [
						{
							"key": "token",
							"value": "{{access_token}}",
							"type": "string"
						}
					]
				},
				"method": "GET",
				"header": [
					{
						"key": "x-user-id",
						"value": "123",
						"type": "text"
					}
				],
				"url": {
					"raw": "http://localhost:8080/books/683e402320a5d5bb9efc4c3e",
					"protocol": "http",
					"host": [
						"localhost"
					],
					"port": "8080",
					"path": [
						"books",
						"683e402320a5d5bb9efc4c3e"
					]
				}
			},
			"response": []
		},
		{
			"name": "List Books Recently Viewed",
			"request": {
				"auth": {
					"type": "bearer",
					"bearer": [
						{
							"key": "token",
							"value": "{{access_token}}",
							"type": "string"
						}
					]
				},
				"method": "GET",
				"header": [],
				"url": {
					"raw": "http://localhost:8080/books/viewed/123",
					"protocol": "http",
					"host": [
						"localhost"
					],
					"port": "8080",
					"path": [
						"books",
						"viewed",
						"123"
					]
				}
			},
			"response": []
		},
		{
			"name": "Get Book By Genre",
			"request": {
				"auth": {
					"type": "bearer",
					"bearer": [
						{
							"key": "token",
							"value": "{{access_token}}",
							"type": "string"
						}
					]
				},
				"method": "GET",
				"header": [],
				"url": {
					"raw": "http://localhost:8080/books/genre/horror",
					"protocol": "http",
					"host": [
						"localhost"
					],
					"port": "8080",
					"path": [
						"books",
						"genre",
						"horror"
					]
				}
			},
			"response": []
		},
		{
			"name": "Get Book By Author",
			"request": {
				"auth": {
					"type": "bearer",
					"bearer": [
						{
							"key": "token",
							"value": "{{access_token}}",
							"type": "string"
						}
					]
				},
				"method": "GET",
				"header": [],
				"url": {
					"raw": "http://localhost:8080/books/author/Myeongseok",
					"protocol": "http",
					"host": [
						"localhost"
					],
					"port": "8080",
					"path": [
						"books",
						"author",
						"Myeongseok"
					]
				}
			},
			"response": []
		},
		{
			"name": "Client Credentials",
			"event": [
				{
					"listen": "test",
					"script": {
						"exec": [
							"var response_data = pm.response.json();\r",
							"console.log(response_data);\r",
							"pm.environment.set(\"access_token\", response_data.access_token);"
						],
						"type": "text/javascript",
						"packages": {}
					}
				}
			],
			"request": {
				"method": "POST",
				"header": [],
				"body": {
					"mode": "urlencoded",
					"urlencoded": [
						{
							"key": "grant_type",
							"value": "client_credentials",
							"type": "text"
						},
						{
							"key": "client_id",
							"value": "code-elevate-client",
							"type": "text"
						},
						{
							"key": "client_secret",
							"value": "bHVpel9jYW50cmVsbGE=",
							"type": "text"
						}
					]
				},
				"url": {
					"raw": "http://localhost:8084/realms/code-elevate-realm/protocol/openid-connect/token",
					"protocol": "http",
					"host": [
						"localhost"
					],
					"port": "8084",
					"path": [
						"realms",
						"code-elevate-realm",
						"protocol",
						"openid-connect",
						"token"
					]
				}
			},
			"response": []
		}
	]
}